docopt_subcommands/__init__.py
docopt_subcommands/subcommands.py
docopt_subcommands-4.0.0.dist-info/LICENSE.txt
docopt_subcommands-4.0.0.dist-info/METADATA
docopt_subcommands-4.0.0.dist-info/WHEEL
docopt_subcommands-4.0.0.dist-info/top_level.txt
docopt_subcommands-4.0.0.dist-info/RECORD
