Metadata-Version: 2.1
Name: docopt-subcommands
Version: 4.0.0
Summary: create subcommand-based CLI programs with docopt
Home-page: https://github.com/abingham/docopt-subcommands
Author: Austin Bingham
Author-email: austin@sixty-north.com
License: MIT License
Keywords: command-line docopt
Platform: UNKNOWN
Classifier: Development Status :: 4 - Beta
Classifier: Programming Language :: Python
Classifier: Programming Language :: Python :: 2.7
Classifier: Programming Language :: Python :: 3
Classifier: Programming Language :: Python :: 3.3
Classifier: Programming Language :: Python :: 3.4
Classifier: Programming Language :: Python :: 3.5
Classifier: Programming Language :: Python :: 3.6
Classifier: Programming Language :: Python :: 3.7
Classifier: Programming Language :: Python :: 3.8
Classifier: License :: OSI Approved :: MIT License
Provides-Extra: test
Provides-Extra: dev
